Metadata-Version: 1.0
Name: trac-LighterTheme
Version: 0.2.1
Summary: A light, Bootstrap-inspired theme for Trac
Home-page: http://trac-hacks.org/wiki/LighterTheme
Author: Ethan Jucovy, Jacqueline Arasi
Author-email: ejucovy@gmail.com
License: BSD
Keywords: trac plugin
Platform: UNKNOWN
